gears/__init__.py
gears/gear.py
gears/history.py
gears/llms/__init__.py
gears/llms/base.py
gears/llms/echo.py
gears/llms/oai.py
gears/utils.py
gearsllm-0.1.28.dist-info/LICENSE
gearsllm-0.1.28.dist-info/METADATA
gearsllm-0.1.28.dist-info/WHEEL
gearsllm-0.1.28.dist-info/RECORD
